opalstack/__init__.py
opalstack/accounts.py
opalstack/addresses.py
opalstack/api.py
opalstack/apps.py
opalstack/certs.py
opalstack/dnsrecords.py
opalstack/domains.py
opalstack/ips.py
opalstack/mailusers.py
opalstack/manager.py
opalstack/mariadbs.py
opalstack/mariausers.py
opalstack/notices.py
opalstack/osusers.py
opalstack/osvars.py
opalstack/psqldbs.py
opalstack/psqlusers.py
opalstack/quarantinedmails.py
opalstack/servers.py
opalstack/sites.py
opalstack/tokens.py
opalstack/usage.py
opalstack/util.py
opalstack-1.0.3.dist-info/LICENSE
opalstack-1.0.3.dist-info/METADATA
opalstack-1.0.3.dist-info/WHEEL
opalstack-1.0.3.dist-info/top_level.txt
opalstack-1.0.3.dist-info/RECORD
