Metadata-Version: 2.1
Name: opalstack
Version: 1.0.3
Summary: Opalstack API Python Library
Home-page: https://github.com/opalstack/opalstack-python
Author: Opalstack
Author-email: support@opalstack.com
License: UNKNOWN
Project-URL: Bug Tracker, https://github.com/opalstack/opalstack-python/issues
Platform: UNKNOWN
Classifier: Programming Language :: Python :: 3
Classifier: License :: OSI Approved :: MIT License
Classifier: Operating System :: OS Independent
Requires-Python: >=3.6
License-File: LICENSE
Requires-Dist: requests
